espncricinfo/__init__.py
espncricinfo/exceptions.py
espncricinfo/match.py
espncricinfo/player.py
espncricinfo/series.py
espncricinfo/summary.py
python_espncricinfo-0.5.8.dist-info/LICENSE.txt
python_espncricinfo-0.5.8.dist-info/METADATA
python_espncricinfo-0.5.8.dist-info/WHEEL
python_espncricinfo-0.5.8.dist-info/top_level.txt
python_espncricinfo-0.5.8.dist-info/zip-safe
python_espncricinfo-0.5.8.dist-info/RECORD
