Metadata-Version: 1.1
Name: python-espncricinfo
Version: 0.5.8
Summary: ESPNCricInfo API client
Home-page: http://github.com/dwillis/python-espncricinfo
Author: Derek Willis
Author-email: dwillis@gmail.com
License: MIT
Keywords: espncricinfo cricket t20 odi
Platform: UNKNOWN
Classifier: Development Status :: 4 - Beta
